ppx/__init__.py
ppx/config.py
ppx/factory.py
ppx/ftp.py
ppx/massive.py
ppx/ppx.py
ppx/pride.py
ppx/project.py
ppx/utils.py
ppx_danokhin-1.4.7.dist-info/licenses/LICENSE
tests/__init__.py
tests/conftest.py
tests/unit_tests/__init__.py
tests/unit_tests/test_cloud.py
tests/unit_tests/test_config.py
tests/unit_tests/test_download.py
tests/unit_tests/test_find_project.py
tests/unit_tests/test_list_projects.py
tests/unit_tests/test_massive.py
tests/unit_tests/test_pride.py
tests/unit_tests/test_utils.py
tests/unit_tests/utils.py
ppx_danokhin-1.4.7.dist-info/METADATA
ppx_danokhin-1.4.7.dist-info/WHEEL
ppx_danokhin-1.4.7.dist-info/entry_points.txt
ppx_danokhin-1.4.7.dist-info/top_level.txt
ppx_danokhin-1.4.7.dist-info/RECORD
